Metadata-Version: 2.4
Name: orekit_jpype
Version: 13.1.3.0
Summary: A space dynamics library. This package is a jpype wrapping of the original orekit java code.
Project-URL: source, https://gitlab.orekit.org/orekit/orekit_jpype/-/tree/master
Project-URL: homepage, https://www.orekit.org/
Project-URL: forum, https://forum.orekit.org/c/orekit-python-wrapper-usage/17
Author-email: Petrus Hyvönen <petrus.hyvonen@gmail.com>
Maintainer-email: Clément Jonglez <clement@jonglez.space>
License: License :: OSI Approved :: Apache Software License
License-File: LICENSE.txt
Classifier: Operating System :: OS Independent
Classifier: Programming Language :: Python :: 3
Classifier: Programming Language :: Python :: 3.8
Classifier: Programming Language :: Python :: 3.9
Classifier: Programming Language :: Python :: 3.10
Classifier: Programming Language :: Python :: 3.11
Classifier: Programming Language :: Python :: 3.12
Classifier: Programming Language :: Python :: 3.13
Classifier: Programming Language :: Python :: 3.14
Classifier: Topic :: Scientific/Engineering
Requires-Python: >=3.8
Requires-Dist: jpype1==1.5.2
Requires-Dist: numpy<2.3
Provides-Extra: dev
Requires-Dist: build; extra == 'dev'
Requires-Dist: coverage; extra == 'dev'
Requires-Dist: flake8; extra == 'dev'
Requires-Dist: flake8-gl-codeclimate; extra == 'dev'
Requires-Dist: jdk4py; extra == 'dev'
Requires-Dist: pytest; extra == 'dev'
Requires-Dist: pytest-cov; extra == 'dev'
Requires-Dist: stubgenj; extra == 'dev'
Provides-Extra: jdk4py
Requires-Dist: jdk4py; extra == 'jdk4py'
Provides-Extra: tests
Requires-Dist: coverage; extra == 'tests'
Requires-Dist: pytest; extra == 'tests'
Requires-Dist: pytest-cov; extra == 'tests'
